asynchronous_fifo.v
module asynchronous_fifo #(
    parameter DSIZE = 8,
    parameter ASIZE = 4
    )(
    input [DSIZE-1:0] wdata,        
    input winc, wclk, wrst_n,       
    input rinc, rclk, rrst_n,       
    output [DSIZE-1:0] rdata,       
    output wfull,                  
    output rempty                   
    );

    wire [ASIZE-1:0] waddr, raddr;
    wire [ASIZE:0] wptr, rptr, wq2_rptr, rq2_wptr;

    two_ff_sync #(ASIZE+1) sync_r2w (       
        .q2(wq2_rptr), 
        .din(rptr),
        .clk(wclk), 
        .rst_n(wrst_n)
    );

    two_ff_sync #(ASIZE+1) sync_w2r (       
        .q2(rq2_wptr), 
        .din(wptr),
        .clk(rclk), 
        .rst_n(rrst_n)
    );

    FIFO_memory #(DSIZE, ASIZE) fifomem(    
        .rdata(rdata), 
        .wdata(wdata),
        .waddr(waddr), 
        .raddr(raddr),
        .wclk_en(winc), 
        .wfull(wfull),
        .wclk(wclk)
    );

    rptr_empty #(ASIZE) rptr_empty(         
        .rempty(rempty),
        .raddr(raddr),
        .rptr(rptr), 
        .rq2_wptr(rq2_wptr),
        .rinc(rinc), 
        .rclk(rclk),
        .rrst_n(rrst_n)
    );

    wptr_full #(ASIZE) wptr_full(           
        .wfull(wfull), 
        .waddr(waddr),
        .wptr(wptr), 
        .wq2_rptr(wq2_rptr),
        .winc(winc), 
        .wclk(wclk),
        .wrst_n(wrst_n)
    );
endmodule

module FIFO_memory #(
    parameter DATA_SIZE = 8,
    parameter ADDR_SIZE = 4
    )(
    input [DATA_SIZE-1:0] wdata,        
    input [ADDR_SIZE-1:0] waddr, raddr,  
    input wclk_en, wfull, wclk,          
    output [DATA_SIZE-1:0] rdata        
    );

    localparam DEPTH = 1<<ADDR_SIZE;     
    reg [DATA_SIZE-1:0] mem [0:DEPTH-1];

    assign rdata = mem[raddr];         

    always @(posedge wclk) begin
        if (wclk_en && !wfull) begin
            mem[waddr] <= wdata; 
        end
    end

endmodule

module rptr_empty #(parameter ADDR_SIZE = 4)(
    input [ADDR_SIZE :0] rq2_wptr,       
    input rinc, rclk, rrst_n,            
    output reg rempty,                  
    output [ADDR_SIZE-1:0] raddr,       
    output reg [ADDR_SIZE :0] rptr      
    );

    reg [ADDR_SIZE:0] rbin;                    
    wire [ADDR_SIZE:0] rgray_next, rbin_next;   
    wire rempty_val;                            

    always @(posedge rclk or negedge rrst_n) begin
        if (!rrst_n) begin               
            {rbin, rptr} <= 0;
        end
        else begin
            {rbin, rptr} <= {rbin_next, rgray_next};  
        end
    end

    assign raddr = rbin[ADDR_SIZE-1:0];                 
    assign rbin_next = rbin + (rinc & ~rempty);         
    assign rgray_next = (rbin_next>>1) ^ rbin_next;     

    assign rempty_val = (rgray_next == rq2_wptr);     

    always @(posedge rclk or negedge rrst_n) begin
        if (!rrst_n) begin           
            rempty <= 1'b1;
        end
        else begin
            rempty <= rempty_val; 
        end
    end
endmodule

module wptr_full #(parameter ADDR_SIZE = 4)(
    input [ADDR_SIZE :0] wq2_rptr,      
    input winc, wclk, wrst_n,            
    output reg wfull,                  
    output [ADDR_SIZE-1:0] waddr,       
    output reg [ADDR_SIZE :0] wptr     
    );

    reg [ADDR_SIZE:0] wbin;                  
    wire [ADDR_SIZE:0] wgray_next, wbin_next;  
    wire wfull_val;                             
    
    always @(posedge wclk or negedge wrst_n) begin
        if (!wrst_n) begin            
            {wbin, wptr} <= 0;
        end
        else begin
            {wbin, wptr} <= {wbin_next, wgray_next}; 
        end
    end

    assign waddr = wbin[ADDR_SIZE-1:0];             
    assign wbin_next = wbin + (winc & ~wfull);      
    assign wgray_next = (wbin_next>>1) ^ wbin_next;    

    assign wfull_val = (wgray_next=={~wq2_rptr[ADDR_SIZE:ADDR_SIZE-1], wq2_rptr[ADDR_SIZE-2:0]});

    always @(posedge wclk or negedge wrst_n) begin
        if (!wrst_n) begin           
            wfull <= 1'b0;
        end
        else begin
            wfull <= wfull_val; 
        end
    end
endmodule

module two_ff_sync #(parameter SIZE = 4)( 
    input [SIZE-1:0] din,       
    input clk, rst_n,           
    output reg [SIZE-1:0] q2   
    );

    reg [SIZE-1:0] q1; 

    always @(posedge clk or negedge rst_n) begin
        if (!rst_n) begin 
            {q2, q1} <= 0;          
        end
        else begin
            {q2, q1} <= {q1, din}; 
        end
    end 
endmodule

asynchronous_fifo_tb.v
`timescale 1ns/1ps
`include "asynchronous_fifo.v"
module asynchronous_fifo_tb();

    parameter DSIZE = 8; 
    parameter ASIZE = 3; 
    parameter DEPTH = 1 << ASIZE; 

    reg [DSIZE-1:0] wdata;  
    wire [DSIZE-1:0] rdata;  
    wire wfull, rempty;     
    reg winc, rinc, wclk, rclk, wrst_n, rrst_n; 

    asynchronous_fifo #(DSIZE, ASIZE) fifo (
        .rdata(rdata), 
        .wdata(wdata),
        .wfull(wfull),
        .rempty(rempty),
        .winc(winc), 
        .rinc(rinc), 
        .wclk(wclk), 
        .rclk(rclk), 
        .wrst_n(wrst_n), 
        .rrst_n(rrst_n)
    );

    integer i=0;
    integer seed = 1;

    always #5 wclk = ~wclk;    
    always #10 rclk = ~rclk;   
    
    initial begin
      
        wclk = 0;
        rclk = 0;
        wrst_n = 1;     
        rrst_n = 1;     
        winc = 0;
        rinc = 0;
        wdata = 0;

    
        #40 wrst_n = 0; rrst_n = 0;
        #40 wrst_n = 1; rrst_n = 1;

        // TEST CASE 1: Write data and read it back
        rinc = 1;
        for (i = 0; i < 10; i = i + 1) begin
            wdata = $random(seed) % 256;
            winc = 1;
            #10;
            winc = 0;
            #10;
        end

        // TEST CASE 2: Write data to make FIFO full and try to write more data
        rinc = 0;
        winc = 1;
        for (i = 0; i < DEPTH + 3; i = i + 1) begin
            wdata = $random(seed) % 256;
            #10;
        end

        // TEST CASE 3: Read data from empty FIFO and try to read more data
        winc = 0;
        rinc = 1;
        for (i = 0; i < DEPTH + 3; i = i + 1) begin
            #20;
        end

        $finish;
    end
    initial begin
        
        $dumpfile("asynchronous_fifo_tb.vcd");
        $dumpvars(0, asynchronous_fifo_tb);    
    end

endmodule

asynchronous_fifo_tb.vcd
$date
	Mon Jan 27 23:20:56 2025
$end
$version
	Icarus Verilog
$end
$timescale
	1ps
$end
$scope module asynchronous_fifo_tb $end
$var wire 1 ! wfull $end
$var wire 1 " rempty $end
$var wire 8 # rdata [7:0] $end
$var parameter 32 $ ASIZE $end
$var parameter 35 % DEPTH $end
$var parameter 32 & DSIZE $end
$var reg 1 ' rclk $end
$var reg 1 ( rinc $end
$var reg 1 ) rrst_n $end
$var reg 1 * wclk $end
$var reg 8 + wdata [7:0] $end
$var reg 1 , winc $end
$var reg 1 - wrst_n $end
$var integer 32 . i [31:0] $end
$var integer 32 / seed [31:0] $end
$scope module fifo $end
$var wire 1 ' rclk $end
$var wire 1 ( rinc $end
$var wire 1 ) rrst_n $end
$var wire 1 * wclk $end
$var wire 8 0 wdata [7:0] $end
$var wire 1 , winc $end
$var wire 1 - wrst_n $end
$var wire 4 1 wq2_rptr [3:0] $end
$var wire 4 2 wptr [3:0] $end
$var wire 1 ! wfull $end
$var wire 3 3 waddr [2:0] $end
$var wire 4 4 rq2_wptr [3:0] $end
$var wire 4 5 rptr [3:0] $end
$var wire 1 " rempty $end
$var wire 8 6 rdata [7:0] $end
$var wire 3 7 raddr [2:0] $end
$var parameter 32 8 ASIZE $end
$var parameter 32 9 DSIZE $end
$scope module fifomem $end
$var wire 8 : rdata [7:0] $end
$var wire 1 * wclk $end
$var wire 1 , wclk_en $end
$var wire 8 ; wdata [7:0] $end
$var wire 1 ! wfull $end
$var wire 3 < waddr [2:0] $end
$var wire 3 = raddr [2:0] $end
$var parameter 32 > ADDR_SIZE $end
$var parameter 32 ? DATA_SIZE $end
$var parameter 35 @ DEPTH $end
$upscope $end
$scope module rptr_empty $end
$var wire 1 ' rclk $end
$var wire 4 A rgray_next [3:0] $end
$var wire 1 ( rinc $end
$var wire 1 ) rrst_n $end
$var wire 4 B rq2_wptr [3:0] $end
$var wire 1 C rempty_val $end
$var wire 4 D rbin_next [3:0] $end
$var wire 3 E raddr [2:0] $end
$var parameter 32 F ADDR_SIZE $end
$var reg 4 G rbin [3:0] $end
$var reg 1 " rempty $end
$var reg 4 H rptr [3:0] $end
$upscope $end
$scope module sync_r2w $end
$var wire 1 * clk $end
$var wire 4 I din [3:0] $end
$var wire 1 - rst_n $end
$var parameter 33 J SIZE $end
$var reg 4 K q1 [3:0] $end
$var reg 4 L q2 [3:0] $end
$upscope $end
$scope module sync_w2r $end
$var wire 1 ' clk $end
$var wire 1 ) rst_n $end
$var wire 4 M din [3:0] $end
$var parameter 33 N SIZE $end
$var reg 4 O q1 [3:0] $end
$var reg 4 P q2 [3:0] $end
$upscope $end
$scope module wptr_full $end
$var wire 1 * wclk $end
$var wire 4 Q wgray_next [3:0] $end
$var wire 1 , winc $end
$var wire 4 R wq2_rptr [3:0] $end
$var wire 1 - wrst_n $end
$var wire 1 S wfull_val $end
$var wire 4 T wbin_next [3:0] $end
$var wire 3 U waddr [2:0] $end
$var parameter 32 V ADDR_SIZE $end
$var reg 4 W wbin [3:0] $end
$var reg 1 ! wfull $end
$var reg 4 X wptr [3:0] $end
$upscope $end
$upscope $end
$upscope $end
$enddefinitions $end
$comment Show the parameter values. $end
$dumpall
b11 V
b100 N
b100 J
b11 F
b1000 @
b1000 ?
b11 >
b1000 9
b11 8
b1000 &
b1000 %
b11 $
$end
#0
$dumpvars
bx X
bx W
bx U
bx T
xS
bx R
bx Q
bx P
bx O
bx M
bx L
bx K
bx I
bx H
bx G
bx E
bx D
xC
bx B
bx A
bx =
bx <
b0 ;
bx :
bx 7
bx 6
bx 5
bx 4
bx 3
bx 2
bx 1
b0 0
b1 /
b0 .
1-
0,
b0 +
0*
1)
0(
0'
bx #
x"
x!
$end
#5000
1*
#10000
0*
1'
#15000
1*
#20000
0*
0'
#25000
1*
#30000
0*
1'
#35000
1*
#40000
1C
0S
b0 7
b0 =
b0 E
b0 A
b0 3
b0 <
b0 U
b0 Q
b0 4
b0 B
b0 P
b0 O
b0 D
b0 G
b0 5
b0 H
b0 I
1"
b0 1
b0 L
b0 R
b0 K
b0 T
b0 W
b0 2
b0 M
b0 X
0!
0*
0'
0)
0-
#45000
1*
#50000
0*
1'
#55000
1*
#60000
0*
0'
#65000
1*
#70000
0*
1'
#75000
1*
#80000
b1 Q
b1 T
0*
0'
1,
b10000110111001110 /
1(
1)
1-
#85000
b1 3
b1 <
b1 U
b11 Q
b0 #
b0 6
b0 :
b10 T
b1 W
b1 2
b1 M
b1 X
1*
#90000
b1 O
b1 Q
b1 T
0*
1'
0,
#95000
1*
#100000
b11 Q
b10 T
0*
0'
1,
b111000 +
b111000 0
b111000 ;
b11100010110011000001111110111 /
b1 .
#105000
b10 3
b10 <
b10 U
b10 Q
b11 T
b10 W
b11 2
b11 M
b11 X
1*
#110000
0C
b1 4
b1 B
b1 P
b11 O
b11 Q
b10 T
0*
1'
0,
#115000
1*
#120000
b10 Q
b11 T
0*
0'
1,
b10000110 +
b10000110 0
b10000110 ;
b11000011010110010011011111001100 /
b10 .
#125000
b11 3
b11 <
b11 U
b110 Q
b100 T
b11 W
b10 2
b10 M
b10 X
1*
#130000
b1 A
b1 D
0"
b11 4
b11 B
b11 P
b10 O
b10 Q
b11 T
0*
1'
0,
#135000
1*
#140000
b110 Q
b100 T
0*
0'
1,
b1011100 +
b1011100 0
b1011100 ;
b101110000100110000101001011101 /
b11 .
#145000
b100 3
b100 <
b100 U
b111 Q
b101 T
b100 W
b110 2
b110 M
b110 X
1*
#150000
b111000 #
b111000 6
b111000 :
b1 7
b1 =
b1 E
0C
b11 A
b10 4
b10 B
b10 P
b110 O
b10 D
b1 G
b1 5
b1 H
b1 I
b110 Q
b100 T
0*
1'
0,
#155000
b1 K
1*
#160000
b111 Q
b101 T
0*
0'
1,
b11001110 +
b11001110 0
b11001110 ;
b11100111001000110000010101111010 /
b100 .
#165000
b101 3
b101 <
b101 U
b101 Q
b110 T
b101 W
b111 2
b111 M
b111 X
b1 1
b1 L
b1 R
1*
#170000
b10000110 #
b10000110 6
b10000110 :
b10 7
b10 =
b10 E
b10 A
b11 D
b10 G
b11 5
b11 H
b11 I
b110 4
b110 B
b110 P
b111 O
b111 Q
b101 T
0*
1'
0,
#175000
b11 K
1*
#180000
b101 Q
b110 T
0*
0'
1,
b11000111 +
b11000111 0
b11000111 ;
b11100011110011001001010010110011 /
b101 .
#185000
b110 3
b110 <
b110 U
b100 Q
b111 T
b110 W
b101 2
b101 M
b101 X
b11 1
b11 L
b11 R
1*
#190000
b1011100 #
b1011100 6
b1011100 :
b11 7
b11 =
b11 E
b110 A
b111 4
b111 B
b111 P
b101 O
b100 D
b11 G
b10 5
b10 H
b10 I
b101 Q
b110 T
0*
1'
0,
#195000
b10 K
1*
#200000
b100 Q
b111 T
0*
0'
1,
b11000110 +
b11000110 0
b11000110 ;
b1100011000100110010101001011000 /
b110 .
#205000
b111 3
b111 <
b111 U
b1100 Q
b1000 T
b111 W
b100 2
b100 M
b100 X
b10 1
b10 L
b10 R
1*
#210000
b11001110 #
b11001110 6
b11001110 :
b100 7
b100 =
b100 E
b111 A
b101 D
b100 G
b110 5
b110 H
b110 I
b101 4
b101 B
b101 P
b100 O
b100 Q
b111 T
0*
1'
0,
#215000
b110 K
1*
#220000
b1100 Q
b1000 T
0*
0'
1,
b11110011 +
b11110011 0
b11110011 ;
b1111001110101110110000001111001 /
b111 .
#225000
b0 3
b0 <
b0 U
b1101 Q
b1001 T
b1000 W
b1100 2
b1100 M
b1100 X
b110 1
b110 L
b110 R
1*
#230000
b11000111 #
b11000111 6
b11000111 :
b101 7
b101 =
b101 E
0C
b101 A
b100 4
b100 B
b100 P
b1100 O
b110 D
b101 G
b111 5
b111 H
b111 I
b1100 Q
b1000 T
0*
1'
0,
#235000
b111 K
1*
#240000
b1101 Q
b1001 T
0*
0'
1,
b11000011 +
b11000011 0
b11000011 ;
b11100001110101110110010111100110 /
b1000 .
#245000
b1 3
b1 <
b1 U
b1111 Q
b1010 T
b1001 W
b1101 2
b1101 M
b1101 X
b111 1
b111 L
b111 R
1*
#250000
b11000110 #
b11000110 6
b11000110 :
b110 7
b110 =
b110 E
b100 A
b111 D
b110 G
b101 5
b101 H
b101 I
b1100 4
b1100 B
b1100 P
b1101 O
b1101 Q
b1001 T
0*
1'
0,
#255000
b101 K
1*
#260000
b1111 Q
b1010 T
0*
0'
1,
b1011111 +
b1011111 0
b1011111 ;
b101111100011110100011100101111 /
b1001 .
#265000
b10 3
b10 <
b10 U
b1110 Q
b1011 T
b1010 W
b1111 2
b1111 M
b1111 X
b101 1
b101 L
b101 R
1*
#270000
b11110011 #
b11110011 6
b11110011 :
b111 7
b111 =
b111 E
b1100 A
b1101 4
b1101 B
b1101 P
b1111 O
b1000 D
b111 G
b100 5
b100 H
b100 I
b1111 Q
b1010 T
0*
1'
0,
#275000
b100 K
1*
#280000
b1110 Q
b100 A
b1011 T
b111 D
0*
0'
b1000111 +
b1000111 0
b1000111 ;
b10100011100010000110001110100100 /
1,
0(
b0 .
#285000
b11 3
b11 <
b11 U
b1010 Q
b1100 T
b1011 W
b1110 2
b1110 M
b1110 X
b100 1
b100 L
b100 R
1*
#290000
b1111 4
b1111 B
b1111 P
b1110 O
0*
1'
b10001001 +
b10001001 0
b10001001 ;
b1000100111010110001111001010101 /
b1 .
#295000
b100 3
b100 <
b100 U
b1011 Q
b1101 T
b1100 W
b1010 2
b1010 M
b1010 X
1*
#300000
0*
0'
b1111110 +
b1111110 0
b1111110 ;
b111111001001101001101100010010 /
b10 .
#305000
b101 3
b101 <
b101 U
0S
b1001 Q
b1110 T
b1101 W
b1011 2
b1011 M
b1011 X
1*
#310000
b1110 4
b1110 B
b1110 P
b1011 O
0*
1'
b1000101 +
b1000101 0
b1000101 ;
b100010110111000001011101101011 /
b11 .
#315000
b110 3
b110 <
b110 U
1S
b1000 Q
b1111 T
b1110 W
b1001 2
b1001 M
b1001 X
1*
#320000
0*
0'
b1011101 +
b1011101 0
b1011101 ;
b101110110110100010111110110000 /
b100 .
#325000
b111 3
b111 <
b111 U
1S
b1000 Q
1!
b1111 T
b1111 W
b1000 2
b1000 M
b1000 X
1*
#330000
b1011 4
b1011 B
b1011 P
b1000 O
0*
1'
b10010001 +
b10010001 0
b10010001 ;
b11001000110101000001111111110001 /
b101 .
#335000
1*
#340000
0*
0'
b1101110 +
b1101110 0
b1101110 ;
b10110111011011011101000011111110 /
b110 .
#345000
1*
#350000
b1000 4
b1000 B
b1000 P
0*
1'
b10001111 +
b10001111 0
b10001111 ;
b1000111100010110100000101100111 /
b111 .
#355000
1*
#360000
0*
0'
b111100 +
b111100 0
b111100 ;
b10011110001111001001101001111100 /
b1000 .
#365000
1*
#370000
0*
1'
b11001001 +
b11001001 0
b11001001 ;
b1100100110111000000000101001101 /
b1001 .
#375000
1*
#380000
0*
0'
b11100011 +
b11100011 0
b11100011 ;
b11110001100010101111001110101010 /
b1010 .
#385000
1*
#390000
b11000011 #
b11000011 6
b11000011 :
b0 7
b0 =
b0 E
b1000 G
b1101 A
b1001 D
0*
1'
1(
0,
b0 .
#395000
1*
#400000
0*
0'
#405000
1*
#410000
b1011111 #
b1011111 6
b1011111 :
b1 7
b1 =
b1 E
b1111 A
b1010 D
b1001 G
b1101 5
b1101 H
b1101 I
0*
1'
b1 .
#415000
b1101 K
1*
#420000
0*
0'
#425000
0S
b1101 1
b1101 L
b1101 R
1*
#430000
b1000111 #
b1000111 6
b1000111 :
b10 7
b10 =
b10 E
b1110 A
b1011 D
b1010 G
b1111 5
b1111 H
b1111 I
0*
1'
b10 .
#435000
b1111 K
0!
1*
#440000
0*
0'
#445000
b1111 1
b1111 L
b1111 R
1*
#450000
b10001001 #
b10001001 6
b10001001 :
b11 7
b11 =
b11 E
b1010 A
b1100 D
b1011 G
b1110 5
b1110 H
b1110 I
0*
1'
b11 .
#455000
b1110 K
1*
#460000
0*
0'
#465000
b1110 1
b1110 L
b1110 R
1*
#470000
b1111110 #
b1111110 6
b1111110 :
b100 7
b100 =
b100 E
b1011 A
b1101 D
b1100 G
b1010 5
b1010 H
b1010 I
0*
1'
b100 .
#475000
b1010 K
1*
#480000
0*
0'
#485000
b1010 1
b1010 L
b1010 R
1*
#490000
b1000101 #
b1000101 6
b1000101 :
b101 7
b101 =
b101 E
0C
b1001 A
b1110 D
b1101 G
b1011 5
b1011 H
b1011 I
0*
1'
b101 .
#495000
b1011 K
1*
#500000
0*
0'
#505000
b1011 1
b1011 L
b1011 R
1*
#510000
b1011101 #
b1011101 6
b1011101 :
b110 7
b110 =
b110 E
1C
b1000 A
b1111 D
b1110 G
b1001 5
b1001 H
b1001 I
0*
1'
b110 .
#515000
b1001 K
1*
#520000
0*
0'
#525000
b1001 1
b1001 L
b1001 R
1*
#530000
b11110011 #
b11110011 6
b11110011 :
b111 7
b111 =
b111 E
1C
b1000 A
1"
b1111 D
b1111 G
b1000 5
b1000 H
b1000 I
0*
1'
b111 .
#535000
b1000 K
1*
#540000
0*
0'
#545000
b1000 1
b1000 L
b1000 R
1*
#550000
0*
1'
b1000 .
#555000
1*
#560000
0*
0'
#565000
1*
#570000
0*
1'
b1001 .
#575000
1*
#580000
0*
0'
#585000
1*
#590000
0*
1'
b1010 .
#595000
1*
#600000
0*
0'
#605000
1*
#610000
0*
1'
b1011 .
